chatglmclient/__init__.py
chatglmclient/chatglm_client.py
chatglmclient/tests/__init__.py
chatglmclient/tests/test_base.py
chatglmclient/tests/feature/__init__.py
chatglmclient/tests/script/__init__.py
chatglmclient/tests/unit/__init__.py
chatglmclient/tests/unit/client_test.py
chatglmclient-0.1.2.dist-info/LICENSE
chatglmclient-0.1.2.dist-info/METADATA
chatglmclient-0.1.2.dist-info/WHEEL
chatglmclient-0.1.2.dist-info/top_level.txt
chatglmclient-0.1.2.dist-info/RECORD
