Metadata-Version: 2.1
Name: chatglmclient
Version: 0.1.2
Summary: chat glm client for api
Home-page: https://gitee.com/jiwei-data/python-chatglm-client.git
Author: jinghewang
Author-email: jinghewang@163.com
License: MIT License
Classifier: Programming Language :: Python :: 3
Classifier: License :: OSI Approved :: MIT License
Classifier: Operating System :: OS Independent
Requires-Python: >=3.10
License-File: LICENSE
